axolotl/__init__.py
axolotl/axolotladdress.py
axolotl/duplicatemessagexception.py
axolotl/identitykey.py
axolotl/identitykeypair.py
axolotl/invalidkeyexception.py
axolotl/invalidkeyidexception.py
axolotl/invalidmessageexception.py
axolotl/invalidversionexception.py
axolotl/legacymessageexception.py
axolotl/nosessionexception.py
axolotl/sessionbuilder.py
axolotl/sessioncipher.py
axolotl/statekeyexchangeexception.py
axolotl/untrustedidentityexception.py
axolotl/ecc/__init__.py
axolotl/ecc/curve.py
axolotl/ecc/djbec.py
axolotl/ecc/ec.py
axolotl/ecc/eckeypair.py
axolotl/groups/__init__.py
axolotl/groups/groupcipher.py
axolotl/groups/groupsessionbuilder.py
axolotl/groups/senderkeyname.py
axolotl/groups/ratchet/__init__.py
axolotl/groups/ratchet/senderchainkey.py
axolotl/groups/ratchet/sendermessagekey.py
axolotl/groups/state/__init__.py
axolotl/groups/state/senderkeyrecord.py
axolotl/groups/state/senderkeystate.py
axolotl/groups/state/senderkeystore.py
axolotl/kdf/__init__.py
axolotl/kdf/derivedmessagesecrets.py
axolotl/kdf/derivedrootsecrets.py
axolotl/kdf/hkdf.py
axolotl/kdf/hkdfv2.py
axolotl/kdf/hkdfv3.py
axolotl/kdf/messagekeys.py
axolotl/protocol/__init__.py
axolotl/protocol/ciphertextmessage.py
axolotl/protocol/keyexchangemessage.py
axolotl/protocol/prekeywhispermessage.py
axolotl/protocol/senderkeydistributionmessage.py
axolotl/protocol/senderkeymessage.py
axolotl/protocol/whispermessage.py
axolotl/protocol/whisperprotos_pb2.py
axolotl/ratchet/__init__.py
axolotl/ratchet/aliceaxolotlparameters.py
axolotl/ratchet/bobaxolotlparamaters.py
axolotl/ratchet/chainkey.py
axolotl/ratchet/ratchetingsession.py
axolotl/ratchet/rootkey.py
axolotl/ratchet/symmetricaxolotlparameters.py
axolotl/state/__init__.py
axolotl/state/axolotlstore.py
axolotl/state/identitykeystore.py
axolotl/state/prekeybundle.py
axolotl/state/prekeyrecord.py
axolotl/state/prekeystore.py
axolotl/state/sessionrecord.py
axolotl/state/sessionstate.py
axolotl/state/sessionstore.py
python_axolotl-0.2.2.dist-info/LICENSE
python_axolotl-0.2.2.dist-info/METADATA
python_axolotl-0.2.2.dist-info/WHEEL
python_axolotl-0.2.2.dist-info/top_level.txt
python_axolotl-0.2.2.dist-info/RECORD
